MANIFEST.in
README.rst
setup.py
ckanext/__init__.py
ckanext/linked_graph/__init__.py
ckanext/linked_graph/controllers.py
ckanext/linked_graph/plugin.py
ckanext/linked_graph/fanstatic/graph.js
ckanext/linked_graph/fanstatic/jqcloud.css
ckanext/linked_graph/public/jqcloud-1.0.4.js
ckanext/linked_graph/templates/graph.html
ckanext/linked_graph/templates/header.html
ckanext/linked_graph/tests/__init__.py
ckanext/linked_graph/tests/test_plugin.py
ckanext_linked_graph.egg-info/PKG-INFO
ckanext_linked_graph.egg-info/SOURCES.txt
ckanext_linked_graph.egg-info/dependency_links.txt
ckanext_linked_graph.egg-info/entry_points.txt
ckanext_linked_graph.egg-info/top_level.txt