Metadata-Version: 1.1
Name: ckanext-linked-graph
Version: 0.0.1
Summary: UNKNOWN
Home-page: https://github.com//ckanext-linked_graph
Author: UNKNOWN
Author-email: UNKNOWN
License: AGPL
Keywords: CKAN
Platform: UNKNOWN
Classifier: Development Status :: 4 - Beta
Classifier: License :: OSI Approved :: GNU Affero General Public License v3 or later (AGPLv3+)
Classifier: Programming Language :: Python :: 2.6
Classifier: Programming Language :: Python :: 2.7
